al_cloud_insight/__init__.py
al_cloud_insight/aims.py
al_cloud_insight/assets.py
al_cloud_insight/azure_explorer.py
al_cloud_insight/cargo.py
al_cloud_insight/cloud_explorer.py
al_cloud_insight/credentials.py
al_cloud_insight/dashboards.py
al_cloud_insight/environments.py
al_cloud_insight/exposures_search.py
al_cloud_insight/informant.py
al_cloud_insight/inquisitor.py
al_cloud_insight/launcher.py
al_cloud_insight/scan_results.py
al_cloud_insight/scan_scheduler.py
al_cloud_insight/sources.py
al_cloud_insight/strawboss.py
al_cloud_insight/tacoma.py
al_cloud_insight/ticket_master.py
al_cloud_insight/usage.py
al_cloud_insight/vulnerabilities.py
al_cloud_insight/watchlist.py
al_cloud_insight-0.0.4.dist-info/DESCRIPTION.rst
al_cloud_insight-0.0.4.dist-info/METADATA
al_cloud_insight-0.0.4.dist-info/RECORD
al_cloud_insight-0.0.4.dist-info/WHEEL
al_cloud_insight-0.0.4.dist-info/metadata.json
al_cloud_insight-0.0.4.dist-info/top_level.txt
