Metadata-Version: 2.0
Name: al-cloud-insight
Version: 0.0.4
Summary: Alert Logic Cloud Insight
Home-page: https://github.com/blade2005/al-cloud-insight
Author: Craig Davis
Author-email: cdavis@alertlogic.com
License: GPLv3
Keywords: cloud-insight alertlogic alert logic
Platform: UNKNOWN
Classifier: Development Status :: 3 - Alpha
Classifier: Intended Audience :: Developers
Classifier: Topic :: Software Development :: Build Tools
Classifier: License :: OSI Approved :: GNU General Public License v3 (GPLv3)
Classifier: Programming Language :: Python :: 2
Classifier: Programming Language :: Python :: 2.7
Requires-Dist: hammock
Requires-Dist: pypng
